nwborglab/.nwborglabsrc.org
nwborglab/__init__.py
nwborglab/assignHandler.py
nwborglab/initHandler.py
nwborglab/main.py
nwborglab/nwborg.py
nwborglab/overview.org
nwborglab/overviewpast.org
nwborglab/overviewsrc.org
nwborglab/scheduleHandler.py
nwborglab/sessionHandler.py
nwborglab/session_skeletons_actual.org
nwborglab/sessionskeletons.org
nwborglab/sessionskeletons.org.org
nwborglab/sessionskeletonssrc.org
nwborglab/subjectHandler.py
nwborglab/surveyHandler.py
nwborglab/terminalTool.py
nwborglab-0.0.67.data/scripts/nwborglab
nwborglab-0.0.67.data/scripts/nwborglabcommand
nwborglab-0.0.67.dist-info/LICENSE
nwborglab-0.0.67.dist-info/METADATA
nwborglab-0.0.67.dist-info/WHEEL
nwborglab-0.0.67.dist-info/top_level.txt
nwborglab-0.0.67.dist-info/RECORD
