Metadata-Version: 2.1
Name: nwborglab
Version: 0.0.67
Summary: Parse, compose, evaluate and execute org files and data in org-down notation.
Home-page: https://github.com/shaneallcroft/nwborglab
Author: Shane Allcroft
Author-email: shaneallcroft@fedoraproject.org
License: UNKNOWN
Project-URL: Bug Tracker, https://github.com/shaneallcroft/nwborglab/issues
Platform: UNKNOWN
Classifier: Programming Language :: Python :: 3
Classifier: License :: OSI Approved :: MIT License
Classifier: Operating System :: OS Independent
Requires-Python: >=3.6
License-File: LICENSE
